LICENSE
MANIFEST.in
README.rst
setup.py
ofcloud/__init__.py
ofcloud/manage.py
ofcloud/ofcloud/__init__.py
ofcloud/ofcloud/api.py
ofcloud/ofcloud/app.py
ofcloud/ofcloud/capstan_utils.py
ofcloud/ofcloud/case_utils.py
ofcloud/ofcloud/local_settings.py.example
ofcloud/ofcloud/models.py
ofcloud/ofcloud/network_utils.py
ofcloud/ofcloud/openstack_utils.py
ofcloud/ofcloud/scheduler_daemon.py
ofcloud/ofcloud/serializers.py
ofcloud/ofcloud/settings.py
ofcloud/ofcloud/urls.py
ofcloud/ofcloud/utils.py
ofcloud/ofcloud/views.py
ofcloud/ofcloud/wsgi.py
ofcloud/ofcloud/management/__init__.py
ofcloud/ofcloud/management/commands/__init__.py
ofcloud/ofcloud/management/commands/restartscheduler.py
ofcloud/ofcloud/management/commands/runscheduler.py
ofcloud/ofcloud/management/commands/terminatescheduler.py
ofcloud/ofcloud/migrations/0001_squashed_0007_instance_snap_task_id.py
ofcloud/ofcloud/migrations/0002_simulation_solver.py
ofcloud/ofcloud/migrations/0003_simulation_count.py
ofcloud/ofcloud/migrations/0004_auto_20161213_2030.py
ofcloud/ofcloud/migrations/0005_instance_status.py
ofcloud/ofcloud/migrations/0006_simulation_status.py
ofcloud/ofcloud/migrations/0007_auto_20170116_1507.py
ofcloud/ofcloud/migrations/0008_auto_20170117_1103.py
ofcloud/ofcloud/migrations/0010_auto_20170124_0825.py
ofcloud/ofcloud/migrations/0011_instance_retry_attempts.py
ofcloud/ofcloud/migrations/0012_auto_20170131_1220.py
ofcloud/ofcloud/migrations/0013_auto_20170317_0956.py
ofcloud/ofcloud/migrations/0014_instance_thread_id.py
ofcloud/ofcloud/migrations/0015_instance_parallelisation.py
ofcloud/ofcloud/migrations/0016_simulation_decomposition.py
ofcloud/ofcloud/migrations/__init__.py
ofcloud/ofcloud/provider/__init__.py
ofcloud/ofcloud/provider/dto.py
ofcloud/ofcloud/provider/provider.py
ofcloud/ofcloud/provider/provider_amazon.py
ofcloud/ofcloud/provider/provider_openstack.py
ofcloud/ofcloud/templates/decomposeParDict_hierarchical
ofcloud/ofcloud/templates/decomposeParDict_manual
openfoam_cloud.egg-info/PKG-INFO
openfoam_cloud.egg-info/SOURCES.txt
openfoam_cloud.egg-info/dependency_links.txt
openfoam_cloud.egg-info/requires.txt
openfoam_cloud.egg-info/top_level.txt