Metadata-Version: 1.1
Name: openfoam-cloud
Version: 1.0
Summary: OpenFOAM Cloud backend application
Home-page: https://www.xlab.si/
Author: XLAB d.o.o.
Author-email: pypi@xlab.si
License: Apache Software License
Platform: UNKNOWN
Classifier: Environment :: Web Environment
Classifier: Intended Audience :: Developers
Classifier: License :: OSI Approved :: Apache Software License
Classifier: Operating System :: OS Independent
Classifier: Programming Language :: Python
Classifier: Programming Language :: Python :: 2.7
